CHANGES.rst
CODE_OF_CONDUCT.md
CONTRIBUTING.md
LICENSE
README.rst
setup.cfg
setup.py
src/senaite/__init__.py
src/senaite.panic.egg-info/PKG-INFO
src/senaite.panic.egg-info/SOURCES.txt
src/senaite.panic.egg-info/dependency_links.txt
src/senaite.panic.egg-info/entry_points.txt
src/senaite.panic.egg-info/namespace_packages.txt
src/senaite.panic.egg-info/not-zip-safe
src/senaite.panic.egg-info/requires.txt
src/senaite.panic.egg-info/top_level.txt
src/senaite/panic/__init__.py
src/senaite/panic/configure.zcml
src/senaite/panic/controlpanel.py
src/senaite/panic/interfaces.py
src/senaite/panic/setuphandlers.py
src/senaite/panic/utils.py
src/senaite/panic/adapters/__init__.py
src/senaite/panic/adapters/configure.zcml
src/senaite/panic/adapters/content.py
src/senaite/panic/adapters/listing.py
src/senaite/panic/browser/__init__.py
src/senaite/panic/browser/configure.zcml
src/senaite/panic/browser/viewlets.py
src/senaite/panic/browser/views.py
src/senaite/panic/browser/templates/panic_alert_email.pt
src/senaite/panic/browser/templates/panic_alert_viewlet.pt
src/senaite/panic/locales/senaite.panic.pot
src/senaite/panic/locales/ca/LC_MESSAGES/senaite.panic.po
src/senaite/panic/locales/cs/LC_MESSAGES/senaite.panic.po
src/senaite/panic/locales/de/LC_MESSAGES/senaite.panic.po
src/senaite/panic/locales/en/LC_MESSAGES/senaite.panic.po
src/senaite/panic/locales/es/LC_MESSAGES/senaite.panic.po
src/senaite/panic/profiles/default/browserlayer.xml
src/senaite/panic/profiles/default/controlpanel.xml
src/senaite/panic/profiles/default/metadata.xml
src/senaite/panic/profiles/default/registry.xml
src/senaite/panic/profiles/default/senaite.panic.install.txt
src/senaite/panic/profiles/uninstall/browserlayer.xml
src/senaite/panic/profiles/uninstall/metadata.xml
src/senaite/panic/profiles/uninstall/senaite.panic.uninstall.txt
src/senaite/panic/static/img/icon.png
src/senaite/panic/static/img/panic.png
src/senaite/panic/static/js/email_popup.js
src/senaite/panic/tests/__init__.py
src/senaite/panic/tests/base.py
src/senaite/panic/tests/test_doctests.py
src/senaite/panic/tests/test_setup.py